backend_utils/__init__.py
backend_utils/http/__init__.py
backend_utils/http/base.py
backend_utils/http/middleware.py
backend_utils/server/__init__.py
backend_utils/server/app/__init__.py
backend_utils/server/app/routers.py
backend_utils/tools/__init__.py
backend_utils/tools/enums.py
backend_utils/tools/singleton.py
backend_utils-0.2.0.dist-info/WHEEL
backend_utils-0.2.0.dist-info/METADATA
backend_utils-0.2.0.dist-info/RECORD
