Metadata-Version: 2.1
Name: backend-utils
Version: 0.2.0
Summary: backend utils
Home-page: https://github.com/Sistemka/backend-utils
Author: Mark Antipin
Author-email: antipinsuperstar@yandex.ru
Requires-Python: >=3.10,<4.0
Classifier: Programming Language :: Python :: 3
Classifier: Programming Language :: Python :: 3.10
Requires-Dist: fastapi (>=0.75.0,<0.76.0)
Requires-Dist: httpx (>=0.22.0,<0.23.0)
Project-URL: Repository, https://github.com/Sistemka/backend-utils.git
